PyUTLoc/__init__.py
PyUTLoc/annotation.py
PyUTLoc/geocoding.py
PyUTLoc/transformation.py
pyutloc-1.0.1.dist-info/licenses/LICENSE.txt
pyutloc-1.0.1.dist-info/METADATA
pyutloc-1.0.1.dist-info/WHEEL
pyutloc-1.0.1.dist-info/entry_points.txt
pyutloc-1.0.1.dist-info/top_level.txt
pyutloc-1.0.1.dist-info/RECORD
