Metadata-Version: 2.4
Name: PyUTLoc
Version: 1.0.1
Summary: PyUTLoc is implemented as a modular Python package designed to address the challenges of heterogeneous spatial location transformation through a unified framework. The implementation follows a layered architecture that separates concerns into distinct functional modules while maintaining interoperability between components. The package consists of three primary modules: annotation, geocoding, and transformation, each serving a specific role in the coordinate processing pipeline.
Home-page: https://github.com/dxl98/PyUTLoc
Author: Xiaoliang Dai
Author-email: 948719798@qq.com
License-File: LICENSE.txt
Requires-Dist: geopy
Requires-Dist: requests
Requires-Dist: geocoder
Requires-Dist: pygeodesy
Requires-Dist: mgrs
Requires-Dist: utm
Requires-Dist: pyproj
Requires-Dist: openlocationcode
Requires-Dist: geohash2
Requires-Dist: maidenhead
Dynamic: author
Dynamic: author-email
Dynamic: description
Dynamic: home-page
Dynamic: license-file
Dynamic: requires-dist
Dynamic: summary
